fanolabsaccobot/__init__.py
fanolabsaccobot-0.1.1.dist-info/LICENSE
fanolabsaccobot-0.1.1.dist-info/METADATA
fanolabsaccobot-0.1.1.dist-info/WHEEL
fanolabsaccobot-0.1.1.dist-info/top_level.txt
fanolabsaccobot-0.1.1.dist-info/RECORD
