Metadata-Version: 2.1
Name: fanolabsaccobot
Version: 0.1.1
Summary: FanoLabs Accobot module for Python3
Home-page: https://git.fanoai.cn/SDKs/accobot-python
Author: Henry Zheng
Author-email: henry.zheng@fano.ai
License: MIT
Platform: UNKNOWN
Requires-Dist: requests
